watson/__init__.py
watson/dev/__init__.py
watson/dev/middleware.py
watson/dev/reloader.py
watson/dev/server.py
watson_dev-3.0.1.dist-info/DESCRIPTION.rst
watson_dev-3.0.1.dist-info/METADATA
watson_dev-3.0.1.dist-info/RECORD
watson_dev-3.0.1.dist-info/WHEEL
watson_dev-3.0.1.dist-info/metadata.json
watson_dev-3.0.1.dist-info/top_level.txt
