Metadata-Version: 2.0
Name: watson-dev
Version: 3.0.1
Summary: Work with WSGI applications locally.
Home-page: http://github.com/watsonpy/watson-dev
Author: Simon Coulton
Author-email: simon at bespohk.com
License: Copyright (c) 2012-2016 Bespohk, and is maintained by multiple
Requires-Dist: watson-common (>=1.1.2)
Provides-Extra: test
Requires-Dist: coverage; extra == 'test'
Requires-Dist: coveralls; extra == 'test'
Requires-Dist: pytest; extra == 'test'
Requires-Dist: pytest-cov; extra == 'test'
